BeyondTheCStandardLibraryZhongwenban/README.md
BeyondTheCStandardLibraryZhongwenban/__init__.py
BeyondTheCStandardLibraryZhongwenban/__main__.py
BeyondTheCStandardLibraryZhongwenban/file.epub
BeyondTheCStandardLibraryZhongwenban/index.html
BeyondTheCStandardLibraryZhongwenban/css/__init__.py
BeyondTheCStandardLibraryZhongwenban/css/annotations.css
BeyondTheCStandardLibraryZhongwenban/css/main.css
BeyondTheCStandardLibraryZhongwenban/css/normalize.css
BeyondTheCStandardLibraryZhongwenban/css/popup.css
BeyondTheCStandardLibraryZhongwenban/font/__init__.py
BeyondTheCStandardLibraryZhongwenban/font/fontello.eot
BeyondTheCStandardLibraryZhongwenban/font/fontello.svg
BeyondTheCStandardLibraryZhongwenban/font/fontello.ttf
BeyondTheCStandardLibraryZhongwenban/font/fontello.woff
BeyondTheCStandardLibraryZhongwenban/img/__init__.py
BeyondTheCStandardLibraryZhongwenban/img/annotator-glyph-sprite.png
BeyondTheCStandardLibraryZhongwenban/img/annotator-icon-sprite.png
BeyondTheCStandardLibraryZhongwenban/img/apple-touch-icon.png
BeyondTheCStandardLibraryZhongwenban/img/cancelfullscreen.png
BeyondTheCStandardLibraryZhongwenban/img/close.png
BeyondTheCStandardLibraryZhongwenban/img/fullscreen.png
BeyondTheCStandardLibraryZhongwenban/img/loader.gif
BeyondTheCStandardLibraryZhongwenban/img/menu-icon.png
BeyondTheCStandardLibraryZhongwenban/img/save.png
BeyondTheCStandardLibraryZhongwenban/img/saved.png
BeyondTheCStandardLibraryZhongwenban/img/settings-s.png
BeyondTheCStandardLibraryZhongwenban/img/settings.png
BeyondTheCStandardLibraryZhongwenban/img/star.png
BeyondTheCStandardLibraryZhongwenban/js/__init__.py
BeyondTheCStandardLibraryZhongwenban/js/epub.js
BeyondTheCStandardLibraryZhongwenban/js/epub.min.js
BeyondTheCStandardLibraryZhongwenban/js/epub.min.map
BeyondTheCStandardLibraryZhongwenban/js/hooks.min.js
BeyondTheCStandardLibraryZhongwenban/js/hooks.min.map
BeyondTheCStandardLibraryZhongwenban/js/reader.js
BeyondTheCStandardLibraryZhongwenban/js/reader.js.map
beyond_the_c_standard_library_zhongwenban-2024.3.1.0.dist-info/METADATA
beyond_the_c_standard_library_zhongwenban-2024.3.1.0.dist-info/WHEEL
beyond_the_c_standard_library_zhongwenban-2024.3.1.0.dist-info/entry_points.txt
beyond_the_c_standard_library_zhongwenban-2024.3.1.0.dist-info/top_level.txt
beyond_the_c_standard_library_zhongwenban-2024.3.1.0.dist-info/RECORD
